{
    "Skills": [
        {
            "AnimationName": "DefaultBlockSkill001",
            "TimeCoolDown": [
                1.0,
                1.0,
                1.0,
                1.0,
                1.0
            ],
            "SlashArray": [
                {
                    "Slash": [
                        1.0
                    ]
                },
                {
                    "Slash": [
                        1.2000000476837159
                    ]
                },
                {
                    "Slash": [
                        1.5
                    ]
                },
                {
                    "Slash": [
                        1.7999999523162842
                    ]
                },
                {
                    "Slash": [
                        2.299999952316284
                    ]
                }
            ],
            "IsUnlocked": true,
            "IsUsing": true,
            "Level": 1,
            "MaxLevel": 5,
            "ExpToUpgradeArray": [
                40,
                50,
                60,
                90,
                100
            ]
        },
        {
            "AnimationName": "DefaultBlockSkill002",
            "TimeCoolDown": [
                1.0,
                1.0,
                1.0,
                1.0,
                1.0
            ],
            "SlashArray": [
                {
                    "Slash": [
                        1.0
                    ]
                },
                {
                    "Slash": [
                        1.2000000476837159
                    ]
                },
                {
                    "Slash": [
                        1.5
                    ]
                },
                {
                    "Slash": [
                        1.7999999523162842
                    ]
                },
                {
                    "Slash": [
                        2.299999952316284
                    ]
                }
            ],
            "IsUnlocked": true,
            "IsUsing": false,
            "Level": 1,
            "MaxLevel": 5,
            "ExpToUpgradeArray": [
                40,
                50,
                60,
                90,
                100
            ]
        },
        {
            "AnimationName": "DefaultFirstNormalSwordSkill",
            "TimeCoolDown": [
                0.0,
                0.0,
                0.0,
                0.0,
                0.0
            ],
            "SlashArray": [
                {
                    "Slash": [
                        1.0
                    ]
                },
                {
                    "Slash": [
                        1.2000000476837159
                    ]
                },
                {
                    "Slash": [
                        1.5
                    ]
                },
                {
                    "Slash": [
                        1.7999999523162842
                    ]
                },
                {
                    "Slash": [
                        2.299999952316284
                    ]
                }
            ],
            "IsUnlocked": false,
            "IsUsing": false,
            "Level": 1,
            "MaxLevel": 5,
            "ExpToUpgradeArray": [
                10,
                20,
                30,
                40,
                50
            ]
        },
        {
            "AnimationName": "DefaultSecondNormalSwordSkill",
            "TimeCoolDown": [
                0.0,
                0.0,
                0.0,
                0.0,
                0.0
            ],
            "SlashArray": [
                {
                    "Slash": [
                        1.0
                    ]
                },
                {
                    "Slash": [
                        1.2000000476837159
                    ]
                },
                {
                    "Slash": [
                        1.5
                    ]
                },
                {
                    "Slash": [
                        1.7999999523162842
                    ]
                },
                {
                    "Slash": [
                        2.299999952316284
                    ]
                }
            ],
            "IsUnlocked": true,
            "IsUsing": true,
            "Level": 1,
            "MaxLevel": 5,
            "ExpToUpgradeArray": [
                10,
                20,
                30,
                40,
                50
            ]
        },
        {
            "AnimationName": "FirstSwordSkill001",
            "TimeCoolDown": [
                10.0,
                9.0,
                9.0,
                8.0,
                8.0
            ],
            "SlashArray": [
                {
                    "Slash": [
                        1.0
                    ]
                },
                {
                    "Slash": [
                        1.2000000476837159
                    ]
                },
                {
                    "Slash": [
                        1.5
                    ]
                },
                {
                    "Slash": [
                        1.7999999523162842
                    ]
                },
                {
                    "Slash": [
                        2.299999952316284
                    ]
                }
            ],
            "IsUnlocked": false,
            "IsUsing": false,
            "Level": 1,
            "MaxLevel": 5,
            "ExpToUpgradeArray": [
                10,
                20,
                30,
                40,
                50
            ]
        },
        {
            "AnimationName": "FirstSwordSkill002",
            "TimeCoolDown": [
                10.0,
                9.0,
                9.0,
                8.0,
                8.0
            ],
            "SlashArray": [
                {
                    "Slash": [
                        1.0
                    ]
                },
                {
                    "Slash": [
                        1.2000000476837159
                    ]
                },
                {
                    "Slash": [
                        1.5
                    ]
                },
                {
                    "Slash": [
                        1.7999999523162842
                    ]
                },
                {
                    "Slash": [
                        2.299999952316284
                    ]
                }
            ],
            "IsUnlocked": true,
            "IsUsing": false,
            "Level": 1,
            "MaxLevel": 5,
            "ExpToUpgradeArray": [
                10,
                20,
                30,
                40,
                50
            ]
        },
        {
            "AnimationName": "FirstSwordSkill003",
            "TimeCoolDown": [
                10.0,
                9.0,
                9.0,
                8.0,
                8.0
            ],
            "SlashArray": [
                {
                    "Slash": [
                        1.0
                    ]
                },
                {
                    "Slash": [
                        1.2000000476837159
                    ]
                },
                {
                    "Slash": [
                        1.5
                    ]
                },
                {
                    "Slash": [
                        1.7999999523162842
                    ]
                },
                {
                    "Slash": [
                        2.299999952316284
                    ]
                }
            ],
            "IsUnlocked": false,
            "IsUsing": false,
            "Level": 1,
            "MaxLevel": 5,
            "ExpToUpgradeArray": [
                10,
                20,
                30,
                40,
                50
            ]
        },
        {
            "AnimationName": "SecondSwordSkill001",
            "TimeCoolDown": [
                15.0,
                15.0,
                14.0,
                14.0,
                13.0
            ],
            "SlashArray": [
                {
                    "Slash": [
                        1.0,
                        1.100000023841858,
                        1.2000000476837159
                    ]
                },
                {
                    "Slash": [
                        1.100000023841858,
                        1.2000000476837159,
                        1.2999999523162842
                    ]
                },
                {
                    "Slash": [
                        1.2000000476837159,
                        1.2999999523162842,
                        1.399999976158142
                    ]
                },
                {
                    "Slash": [
                        1.2999999523162842,
                        1.399999976158142,
                        1.5
                    ]
                },
                {
                    "Slash": [
                        1.399999976158142,
                        1.5,
                        1.600000023841858
                    ]
                }
            ],
            "IsUnlocked": false,
            "IsUsing": false,
            "Level": 1,
            "MaxLevel": 5,
            "ExpToUpgradeArray": [
                20,
                30,
                40,
                50,
                60
            ]
        },
        {
            "AnimationName": "SecondSwordSkill002",
            "TimeCoolDown": [
                15.0,
                15.0,
                14.0,
                14.0,
                13.0
            ],
            "SlashArray": [
                {
                    "Slash": [
                        1.0,
                        1.100000023841858,
                        1.2000000476837159
                    ]
                },
                {
                    "Slash": [
                        1.100000023841858,
                        1.2000000476837159,
                        1.2999999523162842
                    ]
                },
                {
                    "Slash": [
                        1.2000000476837159,
                        1.2999999523162842,
                        1.399999976158142
                    ]
                },
                {
                    "Slash": [
                        1.2999999523162842,
                        1.399999976158142,
                        1.5
                    ]
                },
                {
                    "Slash": [
                        1.399999976158142,
                        1.5,
                        1.600000023841858
                    ]
                }
            ],
            "IsUnlocked": true,
            "IsUsing": false,
            "Level": 1,
            "MaxLevel": 5,
            "ExpToUpgradeArray": [
                20,
                30,
                40,
                50,
                60
            ]
        },
        {
            "AnimationName": "SecondSwordSkill003",
            "TimeCoolDown": [
                15.0,
                15.0,
                14.0,
                14.0,
                13.0
            ],
            "SlashArray": [
                {
                    "Slash": [
                        1.0,
                        1.100000023841858,
                        1.2000000476837159
                    ]
                },
                {
                    "Slash": [
                        1.100000023841858,
                        1.2000000476837159,
                        1.2999999523162842
                    ]
                },
                {
                    "Slash": [
                        1.2000000476837159,
                        1.2999999523162842,
                        1.399999976158142
                    ]
                },
                {
                    "Slash": [
                        1.2999999523162842,
                        1.399999976158142,
                        1.5
                    ]
                },
                {
                    "Slash": [
                        1.399999976158142,
                        1.5,
                        1.600000023841858
                    ]
                }
            ],
            "IsUnlocked": true,
            "IsUsing": false,
            "Level": 1,
            "MaxLevel": 5,
            "ExpToUpgradeArray": [
                20,
                30,
                40,
                50,
                60
            ]
        },
        {
            "AnimationName": "ThirdSwordSkill001",
            "TimeCoolDown": [
                10.0,
                9.0,
                9.0,
                8.0,
                8.0
            ],
            "SlashArray": [
                {
                    "Slash": [
                        1.0
                    ]
                },
                {
                    "Slash": [
                        1.2000000476837159
                    ]
                },
                {
                    "Slash": [
                        1.5
                    ]
                },
                {
                    "Slash": [
                        1.7999999523162842
                    ]
                },
                {
                    "Slash": [
                        2.299999952316284
                    ]
                }
            ],
            "IsUnlocked": false,
            "IsUsing": false,
            "Level": 1,
            "MaxLevel": 5,
            "ExpToUpgradeArray": [
                10,
                20,
                30,
                40,
                50
            ]
        },
        {
            "AnimationName": "ThirdSwordSkill002",
            "TimeCoolDown": [
                10.0,
                9.0,
                9.0,
                8.0,
                8.0
            ],
            "SlashArray": [
                {
                    "Slash": [
                        1.0
                    ]
                },
                {
                    "Slash": [
                        1.2000000476837159
                    ]
                },
                {
                    "Slash": [
                        1.5
                    ]
                },
                {
                    "Slash": [
                        1.7999999523162842
                    ]
                },
                {
                    "Slash": [
                        2.299999952316284
                    ]
                }
            ],
            "IsUnlocked": true,
            "IsUsing": false,
            "Level": 1,
            "MaxLevel": 5,
            "ExpToUpgradeArray": [
                10,
                20,
                30,
                40,
                50
            ]
        },
        {
            "AnimationName": "ThirdSwordSkill003",
            "TimeCoolDown": [
                10.0,
                9.0,
                9.0,
                8.0,
                8.0
            ],
            "SlashArray": [
                {
                    "Slash": [
                        1.0
                    ]
                },
                {
                    "Slash": [
                        1.2000000476837159
                    ]
                },
                {
                    "Slash": [
                        1.5
                    ]
                },
                {
                    "Slash": [
                        1.7999999523162842
                    ]
                },
                {
                    "Slash": [
                        2.299999952316284
                    ]
                }
            ],
            "IsUnlocked": true,
            "IsUsing": false,
            "Level": 1,
            "MaxLevel": 5,
            "ExpToUpgradeArray": [
                10,
                20,
                30,
                40,
                50
            ]
        },
        {
            "AnimationName": "DefaultFirstNormalAxeSkill",
            "TimeCoolDown": [
                0.0,
                0.0,
                0.0,
                0.0,
                0.0
            ],
            "SlashArray": [
                {
                    "Slash": [
                        1.0
                    ]
                },
                {
                    "Slash": [
                        1.2000000476837159
                    ]
                },
                {
                    "Slash": [
                        1.5
                    ]
                },
                {
                    "Slash": [
                        1.7999999523162842
                    ]
                },
                {
                    "Slash": [
                        2.299999952316284
                    ]
                }
            ],
            "IsUnlocked": true,
            "IsUsing": true,
            "Level": 1,
            "MaxLevel": 5,
            "ExpToUpgradeArray": [
                10,
                20,
                30,
                40,
                50
            ]
        },
        {
            "AnimationName": "DefaultSecondNormalAxeSkill",
            "TimeCoolDown": [
                0.0,
                0.0,
                0.0,
                0.0,
                0.0
            ],
            "SlashArray": [
                {
                    "Slash": [
                        1.0
                    ]
                },
                {
                    "Slash": [
                        1.2000000476837159
                    ]
                },
                {
                    "Slash": [
                        1.5
                    ]
                },
                {
                    "Slash": [
                        1.7999999523162842
                    ]
                },
                {
                    "Slash": [
                        2.299999952316284
                    ]
                }
            ],
            "IsUnlocked": true,
            "IsUsing": true,
            "Level": 1,
            "MaxLevel": 5,
            "ExpToUpgradeArray": [
                10,
                20,
                30,
                40,
                50
            ]
        },
        {
            "AnimationName": "FirstAxeSkill001",
            "TimeCoolDown": [
                5.0,
                4.0,
                3.0,
                2.0,
                2.0
            ],
            "SlashArray": [
                {
                    "Slash": [
                        1.0
                    ]
                },
                {
                    "Slash": [
                        1.2000000476837159
                    ]
                },
                {
                    "Slash": [
                        1.5
                    ]
                },
                {
                    "Slash": [
                        1.7999999523162842
                    ]
                },
                {
                    "Slash": [
                        2.299999952316284
                    ]
                }
            ],
            "IsUnlocked": true,
            "IsUsing": true,
            "Level": 5,
            "MaxLevel": 5,
            "ExpToUpgradeArray": [
                10,
                20,
                30,
                40,
                50
            ]
        },
        {
            "AnimationName": "SecondAxeSkill001",
            "TimeCoolDown": [
                25.0,
                23.0,
                21.0,
                19.0,
                16.0
            ],
            "SlashArray": [
                {
                    "Slash": [
                        1.0,
                        1.100000023841858,
                        1.2000000476837159
                    ]
                },
                {
                    "Slash": [
                        1.100000023841858,
                        1.2000000476837159,
                        1.2999999523162842
                    ]
                },
                {
                    "Slash": [
                        1.2000000476837159,
                        1.2999999523162842,
                        1.399999976158142
                    ]
                },
                {
                    "Slash": [
                        1.2999999523162842,
                        1.399999976158142,
                        1.5
                    ]
                },
                {
                    "Slash": [
                        1.399999976158142,
                        1.5,
                        1.600000023841858
                    ]
                }
            ],
            "IsUnlocked": true,
            "IsUsing": true,
            "Level": 5,
            "MaxLevel": 5,
            "ExpToUpgradeArray": [
                20,
                30,
                40,
                50,
                60
            ]
        },
        {
            "AnimationName": "SecondAxeSkill002",
            "TimeCoolDown": [
                25.0,
                23.0,
                21.0,
                19.0,
                16.0
            ],
            "SlashArray": [
                {
                    "Slash": [
                        1.0,
                        1.100000023841858,
                        1.2000000476837159
                    ]
                },
                {
                    "Slash": [
                        1.100000023841858,
                        1.2000000476837159,
                        1.2999999523162842
                    ]
                },
                {
                    "Slash": [
                        1.2000000476837159,
                        1.2999999523162842,
                        1.399999976158142
                    ]
                },
                {
                    "Slash": [
                        1.2999999523162842,
                        1.399999976158142,
                        1.5
                    ]
                },
                {
                    "Slash": [
                        1.399999976158142,
                        1.5,
                        1.600000023841858
                    ]
                }
            ],
            "IsUnlocked": true,
            "IsUsing": false,
            "Level": 1,
            "MaxLevel": 5,
            "ExpToUpgradeArray": [
                20,
                30,
                40,
                50,
                60
            ]
        },
        {
            "AnimationName": "SecondAxeSkill003",
            "TimeCoolDown": [
                25.0,
                23.0,
                21.0,
                19.0,
                16.0
            ],
            "SlashArray": [
                {
                    "Slash": [
                        1.0,
                        1.100000023841858,
                        1.2000000476837159
                    ]
                },
                {
                    "Slash": [
                        1.100000023841858,
                        1.2000000476837159,
                        1.2999999523162842
                    ]
                },
                {
                    "Slash": [
                        1.2000000476837159,
                        1.2999999523162842,
                        1.399999976158142
                    ]
                },
                {
                    "Slash": [
                        1.2999999523162842,
                        1.399999976158142,
                        1.5
                    ]
                },
                {
                    "Slash": [
                        1.399999976158142,
                        1.5,
                        1.600000023841858
                    ]
                }
            ],
            "IsUnlocked": true,
            "IsUsing": false,
            "Level": 1,
            "MaxLevel": 5,
            "ExpToUpgradeArray": [
                20,
                30,
                40,
                50,
                60
            ]
        },
        {
            "AnimationName": "ThirdAxeSkill001",
            "TimeCoolDown": [
                20.0,
                18.0,
                17.0,
                16.0,
                14.0
            ],
            "SlashArray": [
                {
                    "Slash": [
                        1.0
                    ]
                },
                {
                    "Slash": [
                        1.2000000476837159
                    ]
                },
                {
                    "Slash": [
                        1.5
                    ]
                },
                {
                    "Slash": [
                        1.7999999523162842
                    ]
                },
                {
                    "Slash": [
                        2.299999952316284
                    ]
                }
            ],
            "IsUnlocked": true,
            "IsUsing": true,
            "Level": 5,
            "MaxLevel": 5,
            "ExpToUpgradeArray": [
                10,
                20,
                30,
                40,
                50
            ]
        },
        {
            "AnimationName": "ThirdAxeSkill002",
            "TimeCoolDown": [
                20.0,
                18.0,
                17.0,
                16.0,
                14.0
            ],
            "SlashArray": [
                {
                    "Slash": [
                        1.0
                    ]
                },
                {
                    "Slash": [
                        1.2000000476837159
                    ]
                },
                {
                    "Slash": [
                        1.5
                    ]
                },
                {
                    "Slash": [
                        1.7999999523162842
                    ]
                },
                {
                    "Slash": [
                        2.299999952316284
                    ]
                }
            ],
            "IsUnlocked": true,
            "IsUsing": false,
            "Level": 1,
            "MaxLevel": 5,
            "ExpToUpgradeArray": [
                10,
                20,
                30,
                40,
                50
            ]
        },
        {
            "AnimationName": "ThirdAxeSkill003",
            "TimeCoolDown": [
                20.0,
                18.0,
                17.0,
                16.0,
                14.0
            ],
            "SlashArray": [
                {
                    "Slash": [
                        1.0
                    ]
                },
                {
                    "Slash": [
                        1.2000000476837159
                    ]
                },
                {
                    "Slash": [
                        1.5
                    ]
                },
                {
                    "Slash": [
                        1.7999999523162842
                    ]
                },
                {
                    "Slash": [
                        2.299999952316284
                    ]
                }
            ],
            "IsUnlocked": true,
            "IsUsing": false,
            "Level": 1,
            "MaxLevel": 5,
            "ExpToUpgradeArray": [
                10,
                20,
                30,
                40,
                50
            ]
        }
    ]
}